infi.django_rest_utils-1.6.1-py2.7-nspkg.pth
infi/django_rest_utils/__init__.py
infi/django_rest_utils/__version__.py
infi/django_rest_utils/admin.py
infi/django_rest_utils/authentication.py
infi/django_rest_utils/decorators.py
infi/django_rest_utils/filters.py
infi/django_rest_utils/metadata.py
infi/django_rest_utils/models.py
infi/django_rest_utils/pagination.py
infi/django_rest_utils/pluck.py
infi/django_rest_utils/renderers.py
infi/django_rest_utils/rest_utils.py
infi/django_rest_utils/routers.py
infi/django_rest_utils/serializers.py
infi/django_rest_utils/utils.py
infi/django_rest_utils/views.py
infi/django_rest_utils/viewsets.py
infi/django_rest_utils/migrations/0001_initial.py
infi/django_rest_utils/migrations/__init__.py
infi/django_rest_utils/templates/django_rest_utils/api_token_authentication.html
infi/django_rest_utils/templates/django_rest_utils/functions.js
infi/django_rest_utils/templates/django_rest_utils/infinidat_filter.html
infi/django_rest_utils/templates/django_rest_utils/infinidat_json_renderer.html
infi/django_rest_utils/templates/django_rest_utils/infinidat_large_queryset_pagination.html
infi/django_rest_utils/templates/django_rest_utils/infinidat_pagination.html
infi/django_rest_utils/templates/django_rest_utils/infinidat_streaming.html
infi/django_rest_utils/templates/django_rest_utils/ordering_filter.html
infi/django_rest_utils/templates/django_rest_utils/simple_filter.html
infi.django_rest_utils-1.6.1.dist-info/LICENSE
infi.django_rest_utils-1.6.1.dist-info/METADATA
infi.django_rest_utils-1.6.1.dist-info/WHEEL
infi.django_rest_utils-1.6.1.dist-info/entry_points.txt
infi.django_rest_utils-1.6.1.dist-info/namespace_packages.txt
infi.django_rest_utils-1.6.1.dist-info/top_level.txt
infi.django_rest_utils-1.6.1.dist-info/RECORD
