Metadata-Version: 2.1
Name: infi.django-rest-utils
Version: 1.6.1
Summary: Enhancements to django-rest-framework
Home-page: https://github.com/Infinidat/infi.django_rest_utils
Author: Itay Galea
Author-email: igalea@infinidat.com
License: BSD
Platform: UNKNOWN
Classifier: Intended Audience :: Developers
Classifier: Intended Audience :: System Administrators
Classifier: License :: OSI Approved :: BSD License
Classifier: Operating System :: OS Independent
Classifier: Programming Language :: Python :: 2.7
Classifier: Programming Language :: Python :: 3.5
Classifier: Topic :: Software Development :: Libraries :: Python Modules
Requires-Dist: capacity
Requires-Dist: djangorestframework (==3.9.4)
Requires-Dist: docopt
Requires-Dist: setuptools
Requires-Dist: unicodecsv
Requires-Dist: future
